classic/components/__init__.py
classic/components/auto_init.py
classic/components/component.py
classic/components/dataclass_field_aliases.py
classic/components/doublewrap.py
classic/components/extra_annotations.py
classic/components/public_methods.py
classic/components/registries.py
classic/components/types.py
classic_components-1.3.1.dist-info/licenses/LICENSE
classic_components-1.3.1.dist-info/METADATA
classic_components-1.3.1.dist-info/WHEEL
classic_components-1.3.1.dist-info/top_level.txt
classic_components-1.3.1.dist-info/RECORD
